bhklab_project_template/__init__.py
bhklab_project_template/logging_config.py
bhklab_project_template/py.typed
bhklab_project_template/utils.py
bhklab_project_template-0.14.1.dist-info/METADATA
bhklab_project_template-0.14.1.dist-info/WHEEL
bhklab_project_template-0.14.1.dist-info/entry_points.txt
bhklab_project_template-0.14.1.dist-info/licenses/LICENSE.md
bhklab_project_template-0.14.1.dist-info/RECORD
